tokenize_all.py
tokenize_all_code-1.0.18.dist-info/LICENSE
tokenize_all_code-1.0.18.dist-info/METADATA
tokenize_all_code-1.0.18.dist-info/WHEEL
tokenize_all_code-1.0.18.dist-info/top_level.txt
tokenize_all_code-1.0.18.dist-info/RECORD
