Metadata-Version: 2.1
Name: tokenize_all_code
Version: 1.0.18
Summary: Tokenize code snippets.
Author: chand1012
License: MIT License
Project-URL: Homepage, https://github.com/CasualCodersProjects/tokenize_all_code
Classifier: License :: OSI Approved :: MIT License
Classifier: Programming Language :: Python :: 3
Classifier: Operating System :: OS Independent
Requires-Python: >=3.9
License-File: LICENSE
